sk_algorithm/SK.py
sk_algorithm/__init__.py
sk_algorithm-0.1.0.dist-info/licenses/LICENSE
sk_algorithm-0.1.0.dist-info/METADATA
sk_algorithm-0.1.0.dist-info/WHEEL
sk_algorithm-0.1.0.dist-info/top_level.txt
sk_algorithm-0.1.0.dist-info/RECORD
