Metadata-Version: 2.4
Name: sk-algorithm
Version: 0.1.0
Summary: A helper library for ecryption and decryption to message
Author: Kathermytheen sk
Author-email: kathermytheen143143@gmail.com
Classifier: Programming Language :: Python :: 3
Classifier: License :: OSI Approved :: MIT License
Classifier: Operating System :: OS Independent
Requires-Python: >=3.6
License-File: LICENSE
Dynamic: author
Dynamic: author-email
Dynamic: classifier
Dynamic: description
Dynamic: description-content-type
Dynamic: license-file
Dynamic: requires-python
Dynamic: summary
